pyWinhook/HookManager.py
pyWinhook/__init__.py
pyWinhook/_cpyHook.cp37-win_amd64.pyd
pyWinhook/aa hook.py
pyWinhook/cpyHook.py
pyWinhook/doc.py
pyWinhook/example.py
pyWinhook-1.6.2.data/data/Lib/site-packages/pyWinhook/CHANGELOG.txt
pyWinhook-1.6.2.data/data/Lib/site-packages/pyWinhook/LICENSE.txt
pyWinhook-1.6.2.data/data/Lib/site-packages/pyWinhook/README.txt
pyWinhook-1.6.2.data/data/Lib/site-packages/pyWinhook/cpyHook.py
pyWinhook-1.6.2.dist-info/LICENSE.txt
pyWinhook-1.6.2.dist-info/METADATA
pyWinhook-1.6.2.dist-info/WHEEL
pyWinhook-1.6.2.dist-info/top_level.txt
pyWinhook-1.6.2.dist-info/RECORD
