Metadata-Version: 1.1
Name: pyWinhook
Version: 1.6.2
Summary: A pyHook module fork from Peter P. with some updates.
Home-page: https://github.com/Tungsteno74/pyWinhook
Author: Tungsteno
Author-email: contacts00-pywinhook@yahoo.it
License: http://www.opensource.org/licenses/mit-license.php
Download-URL: https://codeload.github.com/Tungsteno74/pyWinhook/zip/1.6.2
Keywords: hook win32 win64 keyboard input user control
Platform: Win32
Platform: Win-amd64
Platform: Win-ia64
Classifier: Development Status :: 5 - Production/Stable
Classifier: Intended Audience :: Developers
Classifier: License :: OSI Approved :: MIT License
Classifier: Programming Language :: Python
Classifier: Topic :: System :: Monitoring
Classifier: Topic :: Software Development :: Libraries :: Python Modules
Classifier: Operating System :: Microsoft :: Windows
